Metadata-Version: 2.1
Name: fast-bert-no-plot
Version: 1.9.2
Summary: AI Library using BERT
Home-page: https://github.com/kaushaltrivedi/fast-bert
Author: Kaushal Trivedi
Author-email: kaushaltrivedi@me.com
License: Apache2
Keywords: BERT NLP deep learning google
Platform: UNKNOWN
Classifier: Intended Audience :: Science/Research
Classifier: License :: OSI Approved :: Apache Software License
Classifier: Programming Language :: Python :: 3
Classifier: Topic :: Scientific/Engineering :: Artificial Intelligence
Requires-Dist: pytorch-lamb
Requires-Dist: tensorboardX
Requires-Dist: fastprogress
Requires-Dist: sklearn
Requires-Dist: spacy
Requires-Dist: seqeval
Requires-Dist: tokenizers (==0.8.1.rc1)
Requires-Dist: transformers (>=3.0.2)
Requires-Dist: pandas
Requires-Dist: python-box
Requires-Dist: more-itertools
